README.md
setup.py
dbdesigner/__init__.py
dbdesigner/__main__.py
dbdesigner.egg-info/PKG-INFO
dbdesigner.egg-info/SOURCES.txt
dbdesigner.egg-info/dependency_links.txt
dbdesigner.egg-info/requires.txt
dbdesigner.egg-info/top_level.txt
dbdesigner/apps/__init__.py
dbdesigner/apps/config.py
dbdesigner/apps/registry.py
dbdesigner/conf/__init__.py
dbdesigner/conf/global_settings.py
dbdesigner/conf/locale/__init__.py
dbdesigner/conf/locale/en/__init__.py
dbdesigner/conf/locale/en/formats.py
dbdesigner/conf/locale/zh_Hans/__init__.py
dbdesigner/conf/locale/zh_Hans/formats.py
dbdesigner/core/__init__.py
dbdesigner/core/exceptions.py
dbdesigner/core/paginator.py
dbdesigner/core/signals.py
dbdesigner/core/signing.py
dbdesigner/core/validators.py
dbdesigner/core/checks/__init__.py
dbdesigner/core/checks/database.py
dbdesigner/core/checks/messages.py
dbdesigner/core/checks/model_checks.py
dbdesigner/core/checks/registry.py
dbdesigner/core/checks/templates.py
dbdesigner/core/checks/translation.py
dbdesigner/core/checks/urls.py
dbdesigner/core/checks/compatibility/__init__.py
dbdesigner/core/checks/security/__init__.py
dbdesigner/core/checks/security/base.py
dbdesigner/core/checks/security/csrf.py
dbdesigner/core/checks/security/sessions.py
dbdesigner/core/files/__init__.py
dbdesigner/core/files/base.py
dbdesigner/core/files/images.py
dbdesigner/core/files/locks.py
dbdesigner/core/files/move.py
dbdesigner/core/files/storage.py
dbdesigner/core/files/temp.py
dbdesigner/core/files/uploadedfile.py
dbdesigner/core/files/uploadhandler.py
dbdesigner/core/files/utils.py
dbdesigner/core/mail/__init__.py
dbdesigner/core/mail/message.py
dbdesigner/core/mail/utils.py
dbdesigner/core/mail/backends/__init__.py
dbdesigner/core/mail/backends/base.py
dbdesigner/core/mail/backends/console.py
dbdesigner/core/mail/backends/dummy.py
dbdesigner/core/mail/backends/filebased.py
dbdesigner/core/mail/backends/locmem.py
dbdesigner/core/mail/backends/smtp.py
dbdesigner/core/management/__init__.py
dbdesigner/core/management/base.py
dbdesigner/core/management/color.py
dbdesigner/core/management/sql.py
dbdesigner/core/management/templates.py
