Metadata-Version: 2.1
Name: dbdesigner
Version: 3.0.0
Summary: DBDesigner
Author: chaos-ma
Author-email: 630950058@qq.com
License: MIT
Classifier: Development Status :: 3 - Alpha
Classifier: Intended Audience :: Developers
Classifier: License :: OSI Approved :: MIT License
Classifier: Programming Language :: Python
Classifier: Programming Language :: Python :: 3
Classifier: Programming Language :: Python :: 3.6
Classifier: Programming Language :: Python :: 3.7
Classifier: Programming Language :: Python :: 3.8
Classifier: Programming Language :: Python :: 3.9
Requires-Dist: mysqlclient
Requires-Dist: psycopg2
Requires-Dist: pytz
Requires-Dist: sqlparse
Requires-Dist: asgiref
